{
    "uuid": "cd106eff-4497-4211-a089-76632b6f4f6b",
    "name": "MAX 069",
    "title": "C++ Basics",
    "assessmentSets": [
        {
            "abbreviation": "G",
            "name": "Gallery",
            "heading": "Gallery of questions using different PrairieLearn elements",
            "color": "orange1",
            "description": "Gallery of PL questions"
        }
    ],
    "options": {
        "useNewQuestionRenderer": true
    },
    "topics": [
        {
            "name": "Gallery",
            "color": "orange1",
            "description": "Gallery of PL questions"
        }
    ],
    "tags": [
        {
            "name": "mariana@prairielearn.com",
            "color": "gray1",
            "description": "Author of the original question"
        }
    ],
    "timezone": "America/Chicago"
}
